{
  "id": "tour_7aee1d33-cbd1-4d3c-ae0b-b738c0a7582d",
  "title": "Ba Na Hills and bridge",
  "short_description": "Rise above Da Nang by cable car to Ba Na Hills, where the Golden Bridge, cool mountain air and French-style streets wait in the clouds.",
  "styles": [
    "grand-expeditions",
    "beach",
    "budget",
    "culture",
    "family",
    "gastronomic-experiences",
    "luxury"
  ],
  "seasonality_start_month": "apr",
  "seasonality_end_month": "nov",
  "priority": 50,
  "created_at": "2026-04-13T08:57:00.020Z",
  "updated_at": "2026-04-30T04:05:50.414Z"
}
